hyper_corr/__init__.py
hyper_corr/_gen_kendall_table.py
hyper_corr/_utils.py
hyper_corr/chatterjeexi.py
hyper_corr/kendalltau.py
hyper_corr/pearsonr.py
hyper_corr/somersd.py
hyper_corr/spearmanr.py
hyper_corr/data/kendall_p_flat.npy
hyper_corr/data/kendall_p_hi.npy
hyper_corr/data/kendall_p_lo.npy
hyper_corr/data/kendall_p_offsets.npy
hyper_corr-0.2.1.dist-info/licenses/LICENSE
hyper_corr-0.2.1.dist-info/licenses/THIRD_PARTY_LICENSES.md
hyper_corr-0.2.1.dist-info/licenses/licenses/SciPy_LICENSE.txt
hyper_corr-0.2.1.dist-info/METADATA
hyper_corr-0.2.1.dist-info/WHEEL
hyper_corr-0.2.1.dist-info/top_level.txt
hyper_corr-0.2.1.dist-info/RECORD
