Metadata-Version: 2.4
Name: hyper_corr
Version: 0.2.1
Summary: Hyper-Fast Correlation Functions (Numba-Accelerated): Pearson's r, Spearman's rho, Kendall's tau, Chatterjee's xi, Somers’ D
Author: Jon Paul Lundquist
License-Expression: MIT
Project-URL: Homepage, https://github.com/JonPaulLundquist/hyper_corr
Project-URL: Issues, https://github.com/JonPaulLundquist/hyper_corr/issues
Keywords: statistics,correlation,ranked,pearson,spearman,kendall,chatterjee,somers,numba
Classifier: Programming Language :: Python :: 3
Classifier: Operating System :: OS Independent
Classifier: Topic :: Scientific/Engineering :: Information Analysis
Requires-Python: >=3.8
License-File: LICENSE
License-File: THIRD_PARTY_LICENSES.md
License-File: licenses/SciPy_LICENSE.txt
Requires-Dist: numba>=0.61
Requires-Dist: numpy>=1.23
Dynamic: license-file
